sync_my_tasks/__init__.py
sync_my_tasks/command.py
sync_my_tasks/provider_asana.py
sync_my_tasks/provider_mstodo.py
sync_my_tasks/task.py
sync_my_tasks/tasklist.py
sync_my_tasks-0.2.0.dist-info/entry_points.txt
sync_my_tasks-0.2.0.dist-info/LICENSE
sync_my_tasks-0.2.0.dist-info/WHEEL
sync_my_tasks-0.2.0.dist-info/METADATA
sync_my_tasks-0.2.0.dist-info/RECORD
