Metadata-Version: 2.1
Name: sync-my-tasks
Version: 0.2.0
Summary: Copy tasks between apps
Home-page: https://github.com/wilrnh/sync-my-tasks
License: MIT
Keywords: tasks,asana,microsoft,todo,import,export
Author: wilrnh
Requires-Python: >=3.9,<4.0
Classifier: License :: OSI Approved :: MIT License
Classifier: Programming Language :: Python :: 3
Classifier: Programming Language :: Python :: 3.10
Classifier: Programming Language :: Python :: 3.9
Requires-Dist: asana (>=0.10.3,<0.11.0)
Requires-Dist: docopt (>=0.6.2,<0.7.0)
Requires-Dist: msal (>=1.16.0,<2.0.0)
Project-URL: Documentation, https://github.com/wilrnh/sync-my-tasks
Project-URL: Repository, https://github.com/wilrnh/sync-my-tasks
